mrkutil/__init__.py
mrkutil/base/__init__.py
mrkutil/base/base_handler.py
mrkutil/cache/__init__.py
mrkutil/cache/base_redis.py
mrkutil/cache/job_cache.py
mrkutil/communication/__init__.py
mrkutil/communication/call_service.py
mrkutil/communication/listen.py
mrkutil/communication/trigger_service.py
mrkutil/enum/__init__.py
mrkutil/enum/job.py
mrkutil/exception/__init__.py
mrkutil/exception/service_exception.py
mrkutil/logging/__init__.py
mrkutil/logging/logging_config.py
mrkutil/logging/logging_formatter.py
mrkutil/pagination/__init__.py
mrkutil/pagination/dependency.py
mrkutil/pagination/mongoengine.py
mrkutil/pagination/sqlalchemy.py
mrkutil/responses/__init__.py
mrkutil/responses/response_helper.py
mrkutil/service/__init__.py
mrkutil/service/run.py
mrkutil/utilities/__init__.py
mrkutil/utilities/utils.py
mrkutil/utilities/sqlalchemy_mixins/__init__.py
mrkutil/utilities/sqlalchemy_mixins/created_mixin.py
mrkutil/utilities/sqlalchemy_mixins/id_mixin.py
mrkutil-2.1.1.dist-info/licenses/LICENSE
mrkutil-2.1.1.dist-info/WHEEL
mrkutil-2.1.1.dist-info/METADATA
mrkutil-2.1.1.dist-info/RECORD
