Metadata-Version: 2.4
Name: mrkutil
Version: 2.1.1
Summary: Python package containing common functions for python service based architecture.
Author-email: Nebojsa Mrkic <mrkic.nebojsa@gmail.com>
Requires-Python: >=3.12
Classifier: License :: OSI Approved :: Apache Software License
License-File: LICENSE
Requires-Dist: RabbitMQPubSub>=1.4.0
Requires-Dist: redis>=4.2.0 ; extra == "extras"
Requires-Dist: sqlalchemy>=2.0.0 ; extra == "extras"
Requires-Dist: orjson>=3.10.18 ; extra == "extras"
Requires-Dist: psycopg[binary]>=3.2.9 ; extra == "extras"
Requires-Dist: pytest ; extra == "tests"
Requires-Dist: pytest-asyncio ; extra == "tests"
Requires-Dist: mock ; extra == "tests"
Requires-Dist: ruff ; extra == "tests"
Requires-Dist: requests ; extra == "tests"
Requires-Dist: pytest-runner ; extra == "tests"
Requires-Dist: pre-commit ; extra == "tests"
Requires-Dist: pytest-mock ; extra == "tests"
Requires-Dist: psycopg ; extra == "tests"
Requires-Dist: coverage ; extra == "tests"
Requires-Dist: coverage-badge ; extra == "tests"
Requires-Dist: mongoengine ; extra == "tests"
Requires-Dist: mongomock>=4.3.0 ; extra == "tests"
Project-URL: Home, https://github.com/ivke-99/mrkutil
Provides-Extra: extras
Provides-Extra: tests
